microsoft/teams/graph/__init__.py
microsoft/teams/graph/auth_provider.py
microsoft/teams/graph/graph.py
microsoft_teams_graph-2.0.0a5.dist-info/METADATA
microsoft_teams_graph-2.0.0a5.dist-info/WHEEL
microsoft_teams_graph-2.0.0a5.dist-info/RECORD
