Metadata-Version: 2.4
Name: microsoft-teams-graph
Version: 2.0.0a5
Summary: The Graph package for a Microsoft Teams agent
Author-email: Microsoft <TeamsAISDKFeedback@microsoft.com>
License: MIT
Keywords: agents,ai,bot,graph,microsoft,teams
Requires-Python: <3.14,>=3.12
Requires-Dist: azure-core>=1.31.0
Requires-Dist: microsoft-teams-common
Requires-Dist: msgraph-sdk<2.0.0,>=1.30.0
Requires-Dist: pyjwt[crypto]>=2.10.0
